crispio/__init__.py
crispio/annotate.py
crispio/cli.py
crispio/crosstalk.py
crispio/features.py
crispio/map.py
crispio/sequences.yml
crispio/utils.py
crispio-0.0.3.dist-info/LICENSE
crispio-0.0.3.dist-info/METADATA
crispio-0.0.3.dist-info/WHEEL
crispio-0.0.3.dist-info/entry_points.txt
crispio-0.0.3.dist-info/top_level.txt
crispio-0.0.3.dist-info/RECORD
