Metadata-Version: 2.1
Name: crispio
Version: 0.0.3
Summary: Designing CRISPR-Cas guide RNAs in bacteria.
Author-email: Eachan Johnson <eachan.johnson@crick.ac.uk>
License: MIT License
Project-URL: Homepage, https://github.com/scbirlab/crispio
Project-URL: Bug Tracker, https://github.com/scbirlab/crispio
Keywords: biology,CRISPR,science,bacteria
Classifier: Development Status :: 3 - Alpha
Classifier: Intended Audience :: Science/Research
Classifier: Topic :: Scientific/Engineering :: Bio-Informatics
Classifier: License :: OSI Approved :: MIT License
Classifier: Programming Language :: Python :: 3.8
Classifier: Programming Language :: Python :: 3.9
Classifier: Programming Language :: Python :: 3.10
Classifier: Programming Language :: Python :: 3.11
Classifier: Programming Language :: Python :: 3.12
Classifier: Programming Language :: Python :: 3 :: Only
Requires-Python: >=3.8
License-File: LICENSE
Requires-Dist: bioino>=0.0.2
Requires-Dist: carabiner-tools>=0.0.4
Requires-Dist: pyyaml
Requires-Dist: nemony
Requires-Dist: streq
Requires-Dist: tqdm
Provides-Extra: fit
Requires-Dist: carabiner-tools[mpl,pd]>=0.0.4; extra == "fit"
Requires-Dist: jax[cuda12]; extra == "fit"
Requires-Dist: numpy; extra == "fit"
Requires-Dist: optax; extra == "fit"
Requires-Dist: pandas; extra == "fit"
Requires-Dist: scipy; extra == "fit"
Requires-Dist: matplotlib; extra == "fit"
